EpicAuthAsync/__init__.py
EpicAuthAsync/typing_definitions.py
epicauthasync-1.0.0.dist-info/METADATA
epicauthasync-1.0.0.dist-info/WHEEL
epicauthasync-1.0.0.dist-info/top_level.txt
epicauthasync-1.0.0.dist-info/RECORD
