Metadata-Version: 2.4
Name: EpicAuthAsync
Version: 1.0.0
Summary: An asynchronous Epic Games authentication library
Author: Pirxcy
Requires-Python: >=3.12
Dynamic: author
